body_organ_analysis/__init__.py
body_organ_analysis/__main__.py
body_organ_analysis/_external/body_composition_analysis/__init__.py
body_organ_analysis/_external/body_composition_analysis/__main__.py
body_organ_analysis/_external/body_composition_analysis/body_parts/__init__.py
body_organ_analysis/_external/body_composition_analysis/body_parts/definition.py
body_organ_analysis/_external/body_composition_analysis/body_parts/postprocess.py
body_organ_analysis/_external/body_composition_analysis/body_regions/__init__.py
body_organ_analysis/_external/body_composition_analysis/body_regions/definition.py
body_organ_analysis/_external/body_composition_analysis/body_regions/postprocess.py
body_organ_analysis/_external/body_composition_analysis/commands.py
body_organ_analysis/_external/body_composition_analysis/infer/__init__.py
body_organ_analysis/_external/body_composition_analysis/infer/infer.py
body_organ_analysis/_external/body_composition_analysis/io.py
body_organ_analysis/_external/body_composition_analysis/report/__init__.py
body_organ_analysis/_external/body_composition_analysis/report/builder.py
body_organ_analysis/_external/body_composition_analysis/report/plots/__init__.py
body_organ_analysis/_external/body_composition_analysis/report/plots/aggregation.py
body_organ_analysis/_external/body_composition_analysis/report/plots/check.py
body_organ_analysis/_external/body_composition_analysis/report/plots/colors.py
body_organ_analysis/_external/body_composition_analysis/report/plots/heatmaps.py
body_organ_analysis/_external/body_composition_analysis/report/plots/overview.py
body_organ_analysis/_external/body_composition_analysis/report/template/base/example/build.py
body_organ_analysis/_external/body_composition_analysis/report/template/base/example/report.html.jinja
body_organ_analysis/_external/body_composition_analysis/report/template/base/example/report.pdf
body_organ_analysis/_external/body_composition_analysis/report/template/base/example/report.png
body_organ_analysis-0.1.5.dist-info/LICENSE
body_organ_analysis-0.1.5.dist-info/METADATA
body_organ_analysis-0.1.5.dist-info/WHEEL
body_organ_analysis-0.1.5.dist-info/entry_points.txt
body_organ_analysis-0.1.5.dist-info/RECORD
