Metadata-Version: 2.1
Name: body-organ-analysis
Version: 0.1.5
Summary: BOA is a tool for segmentation of CT scans developed by the SHIP-AI group at the Institute for Artificial Intelligence in Medicine (https://ship-ai.ikim.nrw/). Combining the TotalSegmentator and the Body Composition Analysis, this tool is capable of analyzing medical images and identifying the different structures within the human body, including bones, muscles, organs, and blood vessels.
Home-page: https://github.com/UMEssen/Body-and-Organ-Analyzer
License: Apache-2.0
Keywords: python,segmentation,nnunet,boa,body composition analysis
Author: Jannis Straus
Author-email: jannis.straus@uk-essen.de
Requires-Python: >=3.9,<3.11
Classifier: License :: OSI Approved :: Apache Software License
Classifier: Programming Language :: Python :: 3
Classifier: Programming Language :: Python :: 3.9
Classifier: Programming Language :: Python :: 3.10
Provides-Extra: pacs
Provides-Extra: storage
Provides-Extra: triton
Requires-Dist: Jinja2 (>=3.0.3,<4.0.0)
Requires-Dist: SimpleITK (>=2.0.1,<3.0.0)
Requires-Dist: WeasyPrint (>=52.5,<53.0)
Requires-Dist: batchgenerators (==0.21)
Requires-Dist: boa-contrast (>=0.1.4,<0.2.0)
Requires-Dist: celery (==5.2.7) ; extra == "pacs"
Requires-Dist: dataclasses-json (>=0.5.7,<0.6.0)
Requires-Dist: dicomweb-client (>=0.59.0,<0.60.0) ; extra == "pacs" or extra == "storage"
Requires-Dist: fury (>=0.8.0,<0.9.0)
Requires-Dist: kaleido (==0.2.1)
Requires-Dist: matplotlib (>=3.6.2,<4.0.0)
Requires-Dist: medpy (>=0.4.0,<0.5.0)
Requires-Dist: nibabel (>=5.1.0,<6.0.0)
Requires-Dist: numpy (>=1.24.0,<2.0.0)
Requires-Dist: p-tqdm (>=1.4.0,<2.0.0)
Requires-Dist: plotly (>=5.3.1,<6.0.0)
Requires-Dist: psutil (>=5.9.4,<6.0.0)
Requires-Dist: psycopg2-binary (>=2.9.9,<3.0.0) ; extra == "pacs"
Requires-Dist: pydicom (>=2.3.1,<3.0.0)
Requires-Dist: pydicom-seg (>=0.4.1,<0.5.0) ; extra == "pacs" or extra == "storage"
Requires-Dist: pywavelets (>=1.1.1,<2.0.0)
Requires-Dist: requests (>=2.28.2,<3.0.0)
Requires-Dist: scikit-learn (==1.3.0)
Requires-Dist: smbprotocol (>=1.10.1,<2.0.0) ; extra == "pacs" or extra == "storage"
Requires-Dist: tqdm (>=4.45.0,<5.0.0)
Requires-Dist: tritonclient[grpc] (>=2.5.0,<3.0.0) ; extra == "triton"
Requires-Dist: unidecode (>=1.3.6,<2.0.0)
Requires-Dist: xlsxwriter (>=3.1.2,<4.0.0)
Requires-Dist: xvfbwrapper (>=0.2.9,<0.3.0)
Project-URL: Repository, https://github.com/UMEssen/Body-and-Organ-Analyzer
